{
  "title": {
    "media": {
      "url": "",
      "caption": "",
      "credit": ""
    },
    "text": {
      "headline": "Countries that were pro-aerosol from the beginning of the pandemic",
      "text": "Some countries ignored the WHO 'beware of fomites' messaging."
    }
  },
  "events": [
    {
      "media": {
        "thumbnail": "",
        "url": "",
        "caption": "",
        "link": "https://covid19.mohw.gov.tw/en/cp-4868-53719-206.html",
        "credit": ""
      },
      "start_date": {
        "year": "2020",
        "month": 1,
        "day": 22
      },
      "text": {
        "headline": "Taiwan: 2 million masks distributed to stores",
        "text": "Over 2 million face masks were released to the four major convenience store chains, pharmacies, and distribution channels over two consecutive days, with spot checks on prices."
      }
    }
  ]}
